CONTRIBUTING.rst
HISTORY.rst
LICENSE
MANIFEST.in
README.rst
setup.cfg
setup.py
docs/Makefile
docs/conf.py
docs/contributing.rst
docs/history.rst
docs/index.rst
docs/installation.rst
docs/make.bat
docs/readme.rst
docs/usage.rst
python_github/__init__.py
python_github/github_object.py
python_github/issue.py
python_github/license.py
python_github/pull_request.py
python_github/python_github.py
python_github/workflow.py
python_github_api.egg-info/PKG-INFO
python_github_api.egg-info/SOURCES.txt
python_github_api.egg-info/dependency_links.txt
python_github_api.egg-info/not-zip-safe
python_github_api.egg-info/requires.txt
python_github_api.egg-info/top_level.txt
tests/__init__.py
tests/test_python_github.py