Metadata-Version: 2.1
Name: python-github-api
Version: 0.1.0
Summary: simple python client library for github rest API
Home-page: https://github.com/hakuturu583/python_github
Author: Masaya Kataoka
Author-email: ms.kataoka@gmail.com
License: Apache Software License 2.0
Keywords: python_github
Platform: UNKNOWN
Classifier: Development Status :: 2 - Pre-Alpha
Classifier: Intended Audience :: Developers
Classifier: License :: OSI Approved :: Apache Software License
Classifier: Natural Language :: English
Classifier: Programming Language :: Python :: 3
Classifier: Programming Language :: Python :: 3.6
Classifier: Programming Language :: Python :: 3.7
Classifier: Programming Language :: Python :: 3.8
Requires-Python: >=3.6
License-File: LICENSE
